vep_mcp/__init__.py
vep_mcp/bridge.py
vep_mcp/cli.py
vep_mcp/main.py
vep_mcp/mcp_server.py
vepmcp-0.1.0.dist-info/licenses/LICENSE
vepmcp-0.1.0.dist-info/METADATA
vepmcp-0.1.0.dist-info/WHEEL
vepmcp-0.1.0.dist-info/entry_points.txt
vepmcp-0.1.0.dist-info/top_level.txt
vepmcp-0.1.0.dist-info/RECORD
