Metadata-Version: 2.4
Name: VEPmcp
Version: 0.1.0
Summary: Model Context Protocol server for interacting with the Variant Effect Prediction (VEP) API from Ensembl.
Author-email: Jules Kreuer <jules.kreuer@uni-tuebingen.de>
License: MIT
Project-URL: Homepage, https://github.com/not-a-feature/VEPmcp
Project-URL: Repository, https://github.com/not-a-feature/VEPmcp
Project-URL: Documentation, https://github.com/not-a-feature/VEPmcp#readme
Project-URL: Issues, https://github.com/not-a-feature/VEPmcp/issues
Classifier: Development Status :: 4 - Beta
Classifier: Intended Audience :: Developers
Classifier: Intended Audience :: Science/Research
Classifier: License :: OSI Approved :: MIT License
Classifier: Programming Language :: Python :: 3
Classifier: Programming Language :: Python :: 3.10
Classifier: Programming Language :: Python :: 3.11
Classifier: Programming Language :: Python :: 3.12
Classifier: Programming Language :: Python :: 3.13
Classifier: Topic :: Scientific/Engineering :: Bio-Informatics
Requires-Python: >=3.10
License-File: LICENSE
Requires-Dist: mcp>=1.0.0
Requires-Dist: aiohttp>=3.8.0
Provides-Extra: dev
Requires-Dist: pytest>=7.0; extra == "dev"
Requires-Dist: pytest-asyncio; extra == "dev"
Requires-Dist: aresponses; extra == "dev"
Requires-Dist: build; extra == "dev"
Requires-Dist: psutil; extra == "dev"
Requires-Dist: ruff; extra == "dev"
Requires-Dist: mypy; extra == "dev"
Requires-Dist: pytest-cov; extra == "dev"
Provides-Extra: test
Requires-Dist: pytest>=7.0; extra == "test"
Requires-Dist: pytest-asyncio; extra == "test"
Requires-Dist: aresponses; extra == "test"
Requires-Dist: pytest-cov; extra == "test"
Dynamic: license-file
